banknote_knn_utils-0.1.6.dist-info/licenses/LICENSE.md
banknote_utils/__ini__.py
banknote_utils/check_missing_value.py
banknote_utils/ensure_output_directory.py
banknote_utils/modeling_utils.py
banknote_utils/visualization_utils.py
banknote_knn_utils-0.1.6.dist-info/METADATA
banknote_knn_utils-0.1.6.dist-info/WHEEL
banknote_knn_utils-0.1.6.dist-info/top_level.txt
banknote_knn_utils-0.1.6.dist-info/RECORD
